hhhash/__init__.py
hhhash/create.py
hhhash-0.4.dist-info/WHEEL
hhhash-0.4.dist-info/LICENSE
hhhash-0.4.dist-info/METADATA
hhhash-0.4.dist-info/RECORD
