Metadata-Version: 2.1
Name: hhhash
Version: 0.4
Summary: HHHash library is calculate HHHash from HTTP servers.
Home-page: https://github.com/adulau/HHHash
Author: Alexandre Dulaunoy
Author-email: a@foo.be
Requires-Python: >=3.6,<4.0
Classifier: License :: OSI Approved :: MIT License
Classifier: Operating System :: OS Independent
Classifier: Programming Language :: Python :: 3
Classifier: Programming Language :: Python :: 3.6
Classifier: Programming Language :: Python :: 3.7
Classifier: Programming Language :: Python :: 3.8
Classifier: Programming Language :: Python :: 3.9
Classifier: Programming Language :: Python :: 3.10
Classifier: Programming Language :: Python :: 3.11
Classifier: Programming Language :: Python :: 3
Requires-Dist: requests (>=2.20.0,<3.0.0)
Project-URL: Repository, https://github.com/adulau/HHHash/issues
